tests/__init__.py
tests/test_adss.py
tests/test_appledos.py
tests/test_caps11.py
tests/test_cmd.py
tests/test_cos300.py
tests/test_decsys.py
tests/test_dms.py
tests/test_dos11.py
tests/test_dos11dectape.py
tests/test_dos11magtest.py
tests/test_files11.py
tests/test_mfs.py
tests/test_misc.py
tests/test_native.py
tests/test_nova_dgdos.py
tests/test_nova_dgdosmagtape.py
tests/test_os8.py
tests/test_pascal.py
tests/test_prodos.py
tests/test_rsts.py
tests/test_rt11.py
tests/test_solo.py
tests/test_tss8.py
tests/test_unixv0.py
tests/test_unixv6.py
tests/dsk/data/g.py
tests/dsk/data/g18.py
xferx/VERSION
xferx/__init__.py
xferx/__main__.py
xferx/abstract.py
xferx/cache.py
xferx/commons.py
xferx/imd.py
xferx/native.py
xferx/uic.py
xferx/volumes.py
xferx/apple/__init__.py
xferx/apple/abstract.py
xferx/apple/appledosfs.py
xferx/apple/commons.py
xferx/apple/disk.py
xferx/apple/disk_copy.py
xferx/apple/mfs.py
xferx/apple/pascalfs.py
xferx/apple/ppm.py
xferx/apple/prodosfs.py
xferx/device/__init__.py
xferx/device/abstract.py
xferx/device/block.py
xferx/device/block_12bit.py
xferx/device/block_18bit.py
xferx/device/rx.py
xferx/device/tape.py
xferx/nova/__init__.py
xferx/nova/dgdosdumpfs.py
xferx/nova/dgdosfs.py
xferx/nova/dgdosmagtapefs.py
xferx/pdp11/__init__.py
xferx/pdp11/abstract.py
xferx/pdp11/caps11fs.py
xferx/pdp11/dos11fs.py
xferx/pdp11/dos11magtapefs.py
xferx/pdp11/files11fs.py
xferx/pdp11/rad50.py
xferx/pdp11/rstsfs.py
xferx/pdp11/rt11fs.py
xferx/pdp11/solofs.py
xferx/pdp15/__init__.py
xferx/pdp15/adssfs.py
xferx/pdp15/dos15fs.py
xferx/pdp7/__init__.py
xferx/pdp7/codes.py
xferx/pdp7/decsysfs.py
xferx/pdp7/opcodes.py
xferx/pdp7/unix0fs.py
xferx/pdp8/__init__.py
xferx/pdp8/cos300fs.py
xferx/pdp8/dmsfs.py
xferx/pdp8/os8fs.py
xferx/pdp8/tss8fs.py
xferx/shell/__init__.py
xferx/shell/batch.py
xferx/shell/cmds.py
xferx/shell/commons.py
xferx/shell/kmon.py
xferx/unix/__init__.py
xferx/unix/commons.py
xferx/unix/unix1fs.py
xferx/unix/unix4fs.py
xferx/unix/unix5fs.py
xferx-3.6.0.dist-info/licenses/LICENSE
xferx-3.6.0.dist-info/METADATA
xferx-3.6.0.dist-info/WHEEL
xferx-3.6.0.dist-info/entry_points.txt
xferx-3.6.0.dist-info/top_level.txt
xferx-3.6.0.dist-info/RECORD
