Metadata-Version: 2.4
Name: xferx
Version: 3.6.0
Summary: XFERX is an utility for transferring files between various file systems.
Author-email: Andrea Bonomi <andrea.bonomi@gmail.com>
License: The MIT License (MIT)
Project-URL: GitHub, https://github.com/andreax79/xferx
Project-URL: Issues, http://github.com/andreax79/xferx/issues
Classifier: Programming Language :: Python :: 3
Classifier: License :: OSI Approved :: MIT License
Classifier: Operating System :: OS Independent
Requires-Python: >=3.7
License-File: LICENSE
Requires-Dist: pyreadline3; platform_system == "Windows"
Provides-Extra: dev
Requires-Dist: pytest; extra == "dev"
Dynamic: license-file
